apierrors/__init__.py
apierrors/__init__.pyi.py
apierrors/py.typed
apierrors/adapters/__init__.py
apierrors/adapters/fastapi_adapter.py
apierrors/errors_models/__init__.py
apierrors/errors_models/http_errors.py
apierrors/errors_models/base/__init__.py
apierrors/errors_models/base/base.py
apierrors/errors_models/base/mixins.py
apierrors/status_codes/__init__.py
apierrors/status_codes/err4xx/__init__.py
apierrors/status_codes/err4xx/err400.py
apierrors/status_codes/err4xx/err401.py
apierrors/status_codes/err4xx/err403.py
apierrors/status_codes/err4xx/err404.py
apierrors/status_codes/err4xx/err405.py
apierrors/status_codes/err4xx/err409.py
apierrors/status_codes/err4xx/err422.py
apierrors-0.0.7.dist-info/licenses/LICENSE
apierrors-0.0.7.dist-info/METADATA
apierrors-0.0.7.dist-info/WHEEL
apierrors-0.0.7.dist-info/top_level.txt
apierrors-0.0.7.dist-info/RECORD
