Metadata-Version: 2.4
Name: apierrors
Version: 0.0.7
Summary: Transport-agnostic, typed error DTOs and envelopes for APIs
Author-email: Artem Tilhanovskii <tikhanovskii.artem@gmail.com>
License: MIT License
Project-URL: Homepage, https://github.com/ArtemTaU/apierrors
Project-URL: Issues, https://github.com/ArtemTaU/apierrors/issues
Keywords: errors,api,http,status-codes,fastapi,exceptions
Classifier: Programming Language :: Python :: 3 :: Only
Classifier: Programming Language :: Python :: 3.11
Classifier: Programming Language :: Python :: 3.12
Classifier: Programming Language :: Python :: 3.13
Classifier: License :: OSI Approved :: MIT License
Classifier: Operating System :: OS Independent
Classifier: Typing :: Typed
Requires-Python: >=3.11
License-File: LICENSE
Dynamic: license-file
